presets/__init__.py
presets-1.0.0.dist-info/LICENSE
presets-1.0.0.dist-info/METADATA
presets-1.0.0.dist-info/WHEEL
presets-1.0.0.dist-info/top_level.txt
presets-1.0.0.dist-info/RECORD
